LICENSE
MANIFEST.in
README.md
pytest.ini
requirements.txt
setup.cfg
setup.py
src/thenewboston/__init__.py
src/thenewboston.egg-info/PKG-INFO
src/thenewboston.egg-info/SOURCES.txt
src/thenewboston.egg-info/dependency_links.txt
src/thenewboston.egg-info/requires.txt
src/thenewboston.egg-info/top_level.txt
src/thenewboston/accounts/__init__.py
src/thenewboston/accounts/key_files.py
src/thenewboston/accounts/manage.py
src/thenewboston/argparser/__init__.py
src/thenewboston/argparser/validators.py
src/thenewboston/base_classes/__init__.py
src/thenewboston/base_classes/fetch_primary_validator_config.py
src/thenewboston/base_classes/initialize_node.py
src/thenewboston/blocks/__init__.py
src/thenewboston/blocks/block.py
src/thenewboston/blocks/signatures.py
src/thenewboston/constants/__init__.py
src/thenewboston/constants/clean.py
src/thenewboston/constants/crawl.py
src/thenewboston/constants/errors.py
src/thenewboston/constants/network.py
src/thenewboston/environment/__init__.py
src/thenewboston/environment/environment_variables.py
src/thenewboston/factories/__init__.py
src/thenewboston/factories/confirmation_service.py
src/thenewboston/factories/created_modified.py
src/thenewboston/factories/network_node.py
src/thenewboston/factories/network_transaction.py
src/thenewboston/factories/network_validator.py
src/thenewboston/models/__init__.py
src/thenewboston/models/confirmation_service.py
src/thenewboston/models/created_modified.py
src/thenewboston/models/network_node.py
src/thenewboston/models/network_transaction.py
src/thenewboston/models/network_validator.py
src/thenewboston/serializers/__init__.py
src/thenewboston/serializers/account_balance.py
src/thenewboston/serializers/configuration.py
src/thenewboston/serializers/confirmation_block_message.py
src/thenewboston/serializers/message.py
src/thenewboston/serializers/network_block.py
src/thenewboston/serializers/network_transaction.py
src/thenewboston/serializers/primary_validator.py
src/thenewboston/third_party/__init__.py
src/thenewboston/third_party/django_redis/__init__.py
src/thenewboston/third_party/django_redis/pool.py
src/thenewboston/third_party/factory/__init__.py
