Metadata-Version: 2.1
Name: thenewboston
Version: 0.2.3
Summary: UNKNOWN
Home-page: https://github.com/thenewboston-developers/thenewboston-python
Author: Bucky Roberts
Author-email: buckyroberts@gmail.com
Maintainer: Thenewboston
License: MIT
Platform: UNKNOWN
Requires-Python: >=3.7
